<?xml version="1.0" encoding="UTF-8"?>
<metadata xml:lang="zh"><Esri><CreaDate>20230904</CreaDate><CreaTime>17061600</CreaTime><ArcGISFormat>1.0</ArcGISFormat><SyncOnce>TRUE</SyncOnce><DataProperties><lineage><Process ToolSource="c:\program files (x86)\arcgis\desktop10.5\ArcToolbox\Toolboxes\Data Management Tools.tbx\CalculateField" Date="20230904" Time="170616">CalculateField union2_几何校正_merge_仿真 Direction "twoway" VB #</Process><Process ToolSource="c:\program files (x86)\arcgis\desktop10.5\ArcToolbox\Toolboxes\Data Management Tools.tbx\CalculateField" Date="20230904" Time="170748">CalculateField union2_几何校正_merge_仿真 Direction "positive" VB #</Process><Process ToolSource="c:\program files (x86)\arcgis\desktop10.5\ArcToolbox\Toolboxes\Data Management Tools.tbx\CalculateField" Date="20230904" Time="170908">CalculateField union2_几何校正_merge_仿真 Direction "positive" VB #</Process><Process ToolSource="c:\program files (x86)\arcgis\desktop10.5\ArcToolbox\Toolboxes\Data Management Tools.tbx\CalculateField" Date="20230904" Time="170931">CalculateField union2_几何校正_merge_仿真 Direction "positive" VB #</Process><Process ToolSource="c:\program files (x86)\arcgis\desktop10.5\ArcToolbox\Toolboxes\Data Management Tools.tbx\CalculateField" Date="20230907" Time="155854">CalculateField union2_几何校正_merge_仿真 Type "inoutline" VB #</Process><Process ToolSource="c:\program files (x86)\arcgis\desktop10.5\ArcToolbox\Toolboxes\Data Management Tools.tbx\CalculateField" Date="20230907" Time="155941">CalculateField union2_几何校正_merge_仿真 Type "inoutline" VB #</Process><Process ToolSource="c:\program files (x86)\arcgis\desktop10.5\ArcToolbox\Toolboxes\Data Management Tools.tbx\CalculateField" Date="20230907" Time="160025">CalculateField union2_几何校正_merge_仿真 Type "inoutline" VB #</Process><Process ToolSource="c:\program files (x86)\arcgis\desktop10.5\ArcToolbox\Toolboxes\Data Management Tools.tbx\CalculateField" Date="20230907" Time="160038">CalculateField union2_几何校正_merge_仿真 Direction "twoway" VB #</Process><Process ToolSource="c:\program files (x86)\arcgis\desktop10.5\ArcToolbox\Toolboxes\Data Management Tools.tbx\CalculateField" Date="20230907" Time="160153">CalculateField union2_几何校正_merge_仿真 Direction "twoway" VB #</Process><Process ToolSource="c:\program files (x86)\arcgis\desktop10.5\ArcToolbox\Toolboxes\Data Management Tools.tbx\CalculateField" Date="20230907" Time="160203">CalculateField union2_几何校正_merge_仿真 Type "inoutline" VB #</Process><Process ToolSource="c:\program files (x86)\arcgis\desktop10.5\ArcToolbox\Toolboxes\Data Management Tools.tbx\CalculateField" Date="20230907" Time="160319">CalculateField union2_几何校正_merge_仿真 Type "inoutline" VB #</Process><Process ToolSource="c:\program files (x86)\arcgis\desktop10.5\ArcToolbox\Toolboxes\Data Management Tools.tbx\CalculateField" Date="20230907" Time="160328">CalculateField union2_几何校正_merge_仿真 Direction "twoway" VB #</Process><Process ToolSource="c:\program files (x86)\arcgis\desktop10.5\ArcToolbox\Toolboxes\Data Management Tools.tbx\CalculateField" Date="20230907" Time="160353">CalculateField union2_几何校正_merge_仿真 Direction "twoway" VB #</Process><Process ToolSource="c:\program files (x86)\arcgis\desktop10.5\ArcToolbox\Toolboxes\Data Management Tools.tbx\CalculateField" Date="20230907" Time="160405">CalculateField union2_几何校正_merge_仿真 Type "inoutline" VB #</Process><Process ToolSource="c:\program files (x86)\arcgis\desktop10.5\ArcToolbox\Toolboxes\Data Management Tools.tbx\CalculateField" Date="20230907" Time="160516">CalculateField union2_几何校正_merge_仿真 Type "inoutline" VB #</Process><Process ToolSource="c:\program files (x86)\arcgis\desktop10.5\ArcToolbox\Toolboxes\Data Management Tools.tbx\CalculateField" Date="20230907" Time="160529">CalculateField union2_几何校正_merge_仿真 Direction "twoway" VB #</Process><Process ToolSource="c:\program files (x86)\arcgis\desktop10.5\ArcToolbox\Toolboxes\Data Management Tools.tbx\CalculateField" Date="20230907" Time="160641">CalculateField union2_几何校正_merge_仿真 Direction "twoway" VB #</Process><Process ToolSource="c:\program files (x86)\arcgis\desktop10.5\ArcToolbox\Toolboxes\Data Management Tools.tbx\CalculateField" Date="20230907" Time="160703">CalculateField union2_几何校正_merge_仿真 Direction "twoway" VB #</Process><Process ToolSource="c:\program files (x86)\arcgis\desktop10.5\ArcToolbox\Toolboxes\Data Management Tools.tbx\CalculateField" Date="20230908" Time="194927">CalculateField union2_几何校正_merge_仿真 Name2 "" VB #</Process><Process ToolSource="c:\program files (x86)\arcgis\desktop10.5\ArcToolbox\Toolboxes\Data Management Tools.tbx\CalculateField" Date="20230908" Time="195023">CalculateField union2_几何校正_merge_仿真 Name2 "Five1" VB #</Process><Process ToolSource="c:\program files (x86)\arcgis\desktop10.5\ArcToolbox\Toolboxes\Data Management Tools.tbx\CalculateField" Date="20230908" Time="195050">CalculateField union2_几何校正_merge_仿真 Name2 "Five2" VB #</Process><Process ToolSource="c:\program files (x86)\arcgis\desktop10.5\ArcToolbox\Toolboxes\Data Management Tools.tbx\CalculateField" Date="20230908" Time="195110">CalculateField union2_几何校正_merge_仿真 Name2 "Five3" VB #</Process><Process ToolSource="c:\program files (x86)\arcgis\desktop10.5\ArcToolbox\Toolboxes\Data Management Tools.tbx\CalculateField" Date="20230908" Time="195136">CalculateField union2_几何校正_merge_仿真 Name2 "Three1" VB #</Process><Process ToolSource="c:\program files (x86)\arcgis\desktop10.5\ArcToolbox\Toolboxes\Data Management Tools.tbx\CalculateField" Date="20230908" Time="195146">CalculateField union2_几何校正_merge_仿真 Name2 "Three2" VB #</Process><Process ToolSource="c:\program files (x86)\arcgis\desktop10.5\ArcToolbox\Toolboxes\Data Management Tools.tbx\CalculateField" Date="20230908" Time="195201">CalculateField union2_几何校正_merge_仿真 Name2 "Three3" VB #</Process><Process ToolSource="c:\program files (x86)\arcgis\desktop10.5\ArcToolbox\Toolboxes\Data Management Tools.tbx\CalculateField" Date="20230908" Time="195221">CalculateField union2_几何校正_merge_仿真 Name2 "Three4" VB #</Process><Process ToolSource="c:\program files (x86)\arcgis\desktop10.5\ArcToolbox\Toolboxes\Data Management Tools.tbx\CalculateField" Date="20230908" Time="195255">CalculateField union2_几何校正_merge_仿真 Name2 "Three5" VB #</Process><Process ToolSource="c:\program files (x86)\arcgis\desktop10.5\ArcToolbox\Toolboxes\Data Management Tools.tbx\CalculateField" Date="20230908" Time="195309">CalculateField union2_几何校正_merge_仿真 Name2 "Four1" VB #</Process><Process ToolSource="c:\program files (x86)\arcgis\desktop10.5\ArcToolbox\Toolboxes\Data Management Tools.tbx\CalculateField" Date="20230908" Time="195327">CalculateField union2_几何校正_merge_仿真 Name2 "Four2" VB #</Process><Process ToolSource="c:\program files (x86)\arcgis\desktop10.5\ArcToolbox\Toolboxes\Data Management Tools.tbx\CalculateField" Date="20230908" Time="195346">CalculateField union2_几何校正_merge_仿真 Name2 "Four3" VB #</Process><Process ToolSource="c:\program files (x86)\arcgis\desktop10.5\ArcToolbox\Toolboxes\Data Management Tools.tbx\CalculateField" Date="20230908" Time="195356">CalculateField union2_几何校正_merge_仿真 Name2 "Four4" VB #</Process><Process ToolSource="c:\program files (x86)\arcgis\desktop10.5\ArcToolbox\Toolboxes\Data Management Tools.tbx\CalculateField" Date="20230908" Time="195416">CalculateField union2_几何校正_merge_仿真 Name2 "six1" VB #</Process><Process ToolSource="c:\program files (x86)\arcgis\desktop10.5\ArcToolbox\Toolboxes\Data Management Tools.tbx\CalculateField" Date="20230908" Time="195425">CalculateField union2_几何校正_merge_仿真 Name2 "six2" VB #</Process><Process ToolSource="c:\program files (x86)\arcgis\desktop10.5\ArcToolbox\Toolboxes\Data Management Tools.tbx\CalculateField" Date="20230908" Time="195442">CalculateField union2_几何校正_merge_仿真 Name2 "six3" VB #</Process><Process ToolSource="c:\program files (x86)\arcgis\desktop10.5\ArcToolbox\Toolboxes\Data Management Tools.tbx\CalculateField" Date="20230908" Time="195515">CalculateField union2_几何校正_merge_仿真 Name2 "two2" VB #</Process><Process ToolSource="c:\program files (x86)\arcgis\desktop10.5\ArcToolbox\Toolboxes\Data Management Tools.tbx\CalculateField" Date="20230908" Time="195526">CalculateField union2_几何校正_merge_仿真 Name2 "two1" VB #</Process><Process ToolSource="c:\program files (x86)\arcgis\desktop10.5\ArcToolbox\Toolboxes\Data Management Tools.tbx\CalculateField" Date="20230908" Time="195558">CalculateField union2_几何校正_merge_仿真 Name2 "two3" VB #</Process><Process ToolSource="c:\program files (x86)\arcgis\desktop10.5\ArcToolbox\Toolboxes\Data Management Tools.tbx\CalculateField" Date="20230908" Time="195609">CalculateField union2_几何校正_merge_仿真 Name2 "one1" VB #</Process><Process ToolSource="c:\program files (x86)\arcgis\desktop10.5\ArcToolbox\Toolboxes\Data Management Tools.tbx\CalculateField" Date="20230908" Time="195624">CalculateField union2_几何校正_merge_仿真 Name2 "one2" VB #</Process><Process ToolSource="c:\program files (x86)\arcgis\desktop10.5\ArcToolbox\Toolboxes\Data Management Tools.tbx\CalculateField" Date="20230908" Time="195643">CalculateField union2_几何校正_merge_仿真 Name2 "one3" VB #</Process><Process ToolSource="c:\program files (x86)\arcgis\desktop10.5\ArcToolbox\Toolboxes\Data Management Tools.tbx\CalculateField" Date="20230908" Time="195659">CalculateField union2_几何校正_merge_仿真 Name2 "one4" VB #</Process><Process ToolSource="c:\program files (x86)\arcgis\desktop10.5\ArcToolbox\Toolboxes\Data Management Tools.tbx\CalculateField" Date="20230908" Time="195717">CalculateField union2_几何校正_merge_仿真 Name2 "one5" VB #</Process><Process ToolSource="c:\program files (x86)\arcgis\desktop10.5\ArcToolbox\Toolboxes\Data Management Tools.tbx\CalculateField" Date="20230908" Time="195729">CalculateField union2_几何校正_merge_仿真 Name2 "one6" VB #</Process><Process ToolSource="c:\program files (x86)\arcgis\desktop10.5\ArcToolbox\Toolboxes\Data Management Tools.tbx\CalculateField" Date="20230908" Time="195742">CalculateField union2_几何校正_merge_仿真 Name2 "one7" VB #</Process><Process ToolSource="c:\program files (x86)\arcgis\desktop10.5\ArcToolbox\Toolboxes\Data Management Tools.tbx\CalculateField" Date="20230908" Time="195752">CalculateField union2_几何校正_merge_仿真 Name2 "one8" VB #</Process><Process ToolSource="c:\program files (x86)\arcgis\desktop10.5\ArcToolbox\Toolboxes\Data Management Tools.tbx\CalculateField" Date="20230911" Time="131451">CalculateField union2_几何校正_merge_仿真 Name2 "05L_23R" VB #</Process><Process ToolSource="c:\program files (x86)\arcgis\desktop10.5\ArcToolbox\Toolboxes\Data Management Tools.tbx\CalculateField" Date="20230911" Time="131830">CalculateField union2_几何校正_merge_仿真 Name2 "05R_23L" VB #</Process><Process ToolSource="c:\program files (x86)\arcgis\desktop10.5\ArcToolbox\Toolboxes\Data Management Tools.tbx\CalculateField" Date="20230911" Time="131847">CalculateField union2_几何校正_merge_仿真 Name2 "05R_23L" VB #</Process><Process ToolSource="c:\program files (x86)\arcgis\desktop10.5\ArcToolbox\Toolboxes\Data Management Tools.tbx\CalculateField" Date="20230911" Time="131858">CalculateField union2_几何校正_merge_仿真 Name2 "05L_23R" VB #</Process><Process ToolSource="c:\program files (x86)\arcgis\desktop10.5\ArcToolbox\Toolboxes\Data Management Tools.tbx\CalculateField" Date="20230911" Time="131941">CalculateField union2_几何校正_merge_仿真 Name2 "05L_23R" VB #</Process><Process ToolSource="c:\program files (x86)\arcgis\desktop10.5\ArcToolbox\Toolboxes\Data Management Tools.tbx\CalculateField" Date="20230911" Time="131953">CalculateField union2_几何校正_merge_仿真 Name2 "05R_23L" VB #</Process><Process ToolSource="c:\program files (x86)\arcgis\desktop10.5\ArcToolbox\Toolboxes\Data Management Tools.tbx\CalculateField" Date="20230911" Time="132228">CalculateField union2_几何校正_merge_仿真 Name2 "05R_23L" VB #</Process><Process ToolSource="c:\program files (x86)\arcgis\desktop10.5\ArcToolbox\Toolboxes\Data Management Tools.tbx\CalculateField" Date="20231128" Time="164249">CalculateField union2_merge Name2 "C_F" VB #</Process><Process ToolSource="c:\program files (x86)\arcgis\desktop10.5\ArcToolbox\Toolboxes\Data Management Tools.tbx\CalculateField" Date="20231128" Time="165409">CalculateField union2_merge Name2 "F_T6" VB #</Process><Process ToolSource="c:\program files (x86)\arcgis\desktop10.5\ArcToolbox\Toolboxes\Data Management Tools.tbx\CalculateField" Date="20231128" Time="165512">CalculateField union2_merge Name2 "E_T6" VB #</Process><Process ToolSource="c:\program files (x86)\arcgis\desktop10.5\ArcToolbox\Toolboxes\Data Management Tools.tbx\CalculateField" Date="20231128" Time="165546">CalculateField union2_merge Name2 "E_C" VB #</Process><Process ToolSource="c:\program files (x86)\arcgis\desktop10.5\ArcToolbox\Toolboxes\Data Management Tools.tbx\CalculateField" Date="20231128" Time="165657">CalculateField union2_merge Name2 "D_D2_E_F" VB #</Process><Process ToolSource="c:\program files (x86)\arcgis\desktop10.5\ArcToolbox\Toolboxes\Data Management Tools.tbx\CalculateField" Date="20231128" Time="165733">CalculateField union2_merge Name2 "C1_D_D1" VB #</Process><Process ToolSource="c:\program files (x86)\arcgis\desktop10.5\ArcToolbox\Toolboxes\Data Management Tools.tbx\CalculateField" Date="20231128" Time="165753">CalculateField union2_merge Name2 "C_C1" VB #</Process><Process ToolSource="c:\program files (x86)\arcgis\desktop10.5\ArcToolbox\Toolboxes\Data Management Tools.tbx\CalculateField" Date="20231128" Time="165932">CalculateField union2_merge Name2 "D_C3_D3" VB #</Process><Process ToolSource="c:\program files (x86)\arcgis\desktop10.5\ArcToolbox\Toolboxes\Data Management Tools.tbx\CalculateField" Date="20231128" Time="170029">CalculateField union2_merge Name2 "C_C3" VB #</Process><Process ToolSource="c:\program files (x86)\arcgis\desktop10.5\ArcToolbox\Toolboxes\Data Management Tools.tbx\CalculateField" Date="20231128" Time="170049">CalculateField union2_merge Name2 "C_C4" VB #</Process><Process ToolSource="c:\program files (x86)\arcgis\desktop10.5\ArcToolbox\Toolboxes\Data Management Tools.tbx\CalculateField" Date="20231128" Time="170126">CalculateField union2_merge Name2 "D_D4_C4" VB #</Process><Process ToolSource="c:\program files (x86)\arcgis\desktop10.5\ArcToolbox\Toolboxes\Data Management Tools.tbx\CalculateField" Date="20231128" Time="170144">CalculateField union2_merge Name2 "C_C5" VB #</Process><Process ToolSource="c:\program files (x86)\arcgis\desktop10.5\ArcToolbox\Toolboxes\Data Management Tools.tbx\CalculateField" Date="20231128" Time="170206">CalculateField union2_merge Name2 "D_C5" VB #</Process><Process ToolSource="c:\program files (x86)\arcgis\desktop10.5\ArcToolbox\Toolboxes\Data Management Tools.tbx\CalculateField" Date="20231128" Time="170249">CalculateField union2_merge Name2 "D_D5_C6" VB #</Process><Process ToolSource="c:\program files (x86)\arcgis\desktop10.5\ArcToolbox\Toolboxes\Data Management Tools.tbx\CalculateField" Date="20231128" Time="170306">CalculateField union2_merge Name2 "C_C6" VB #</Process><Process ToolSource="c:\program files (x86)\arcgis\desktop10.5\ArcToolbox\Toolboxes\Data Management Tools.tbx\CalculateField" Date="20231128" Time="170320">CalculateField union2_merge Name2 "C_C7" VB #</Process><Process ToolSource="c:\program files (x86)\arcgis\desktop10.5\ArcToolbox\Toolboxes\Data Management Tools.tbx\CalculateField" Date="20231128" Time="170352">CalculateField union2_merge Name2 "D_C7_D6" VB #</Process><Process ToolSource="c:\program files (x86)\arcgis\desktop10.5\ArcToolbox\Toolboxes\Data Management Tools.tbx\CalculateField" Date="20231128" Time="170415">CalculateField union2_merge Name2 "D_G" VB #</Process><Process ToolSource="c:\program files (x86)\arcgis\desktop10.5\ArcToolbox\Toolboxes\Data Management Tools.tbx\CalculateField" Date="20231128" Time="170425">CalculateField union2_merge Name2 "D_H" VB #</Process><Process ToolSource="c:\program files (x86)\arcgis\desktop10.5\ArcToolbox\Toolboxes\Data Management Tools.tbx\CalculateField" Date="20231128" Time="170440">CalculateField union2_merge Name2 "C_G" VB #</Process><Process ToolSource="c:\program files (x86)\arcgis\desktop10.5\ArcToolbox\Toolboxes\Data Management Tools.tbx\CalculateField" Date="20231128" Time="170457">CalculateField union2_merge Name2 "C_H" VB #</Process><Process ToolSource="c:\program files (x86)\arcgis\desktop10.5\ArcToolbox\Toolboxes\Data Management Tools.tbx\CalculateField" Date="20231128" Time="170521">CalculateField union2_merge Name2 "D_D7_C8" VB #</Process><Process ToolSource="c:\program files (x86)\arcgis\desktop10.5\ArcToolbox\Toolboxes\Data Management Tools.tbx\CalculateField" Date="20231128" Time="170537">CalculateField union2_merge Name2 "C_C8" VB #</Process><Process ToolSource="c:\program files (x86)\arcgis\desktop10.5\ArcToolbox\Toolboxes\Data Management Tools.tbx\CalculateField" Date="20231128" Time="170556">CalculateField union2_merge Name2 "C9_D8_D" VB #</Process><Process ToolSource="c:\program files (x86)\arcgis\desktop10.5\ArcToolbox\Toolboxes\Data Management Tools.tbx\CalculateField" Date="20231128" Time="173730">CalculateField union2_merge Name2 "C_C9" VB #</Process><Process ToolSource="c:\program files (x86)\arcgis\desktop10.5\ArcToolbox\Toolboxes\Data Management Tools.tbx\CalculateField" Date="20231128" Time="173809">CalculateField union2_merge Name2 "T8_C9" VB #</Process><Process ToolSource="c:\program files (x86)\arcgis\desktop10.5\ArcToolbox\Toolboxes\Data Management Tools.tbx\CalculateField" Date="20231128" Time="173829">CalculateField union2_merge Name2 "G3_C9" VB #</Process><Process ToolSource="c:\program files (x86)\arcgis\desktop10.5\ArcToolbox\Toolboxes\Data Management Tools.tbx\CalculateField" Date="20231128" Time="173903">CalculateField union2_merge Name2 "G3_H" VB #</Process><Process ToolSource="c:\program files (x86)\arcgis\desktop10.5\ArcToolbox\Toolboxes\Data Management Tools.tbx\CalculateField" Date="20231128" Time="173918">CalculateField union2_merge Name2 "T8_H" VB #</Process><Process ToolSource="c:\program files (x86)\arcgis\desktop10.5\ArcToolbox\Toolboxes\Data Management Tools.tbx\CalculateField" Date="20231128" Time="173929">CalculateField union2_merge Name2 "T8_G" VB #</Process><Process ToolSource="c:\program files (x86)\arcgis\desktop10.5\ArcToolbox\Toolboxes\Data Management Tools.tbx\CalculateField" Date="20231128" Time="173943">CalculateField union2_merge Name2 "G3_G" VB #</Process><Process ToolSource="c:\program files (x86)\arcgis\desktop10.5\ArcToolbox\Toolboxes\Data Management Tools.tbx\CalculateField" Date="20231128" Time="174002">CalculateField union2_merge Name2 "G3_N3" VB #</Process><Process ToolSource="c:\program files (x86)\arcgis\desktop10.5\ArcToolbox\Toolboxes\Data Management Tools.tbx\CalculateField" Date="20231128" Time="174015">CalculateField union2_merge Name2 "T8_N3" VB #</Process><Process ToolSource="c:\program files (x86)\arcgis\desktop10.5\ArcToolbox\Toolboxes\Data Management Tools.tbx\CalculateField" Date="20231128" Time="174031">CalculateField union2_merge Name2 "G_G2" VB #</Process><Process ToolSource="c:\program files (x86)\arcgis\desktop10.5\ArcToolbox\Toolboxes\Data Management Tools.tbx\CalculateField" Date="20231128" Time="174041">CalculateField union2_merge Name2 "H_G2" VB #</Process><Process ToolSource="c:\program files (x86)\arcgis\desktop10.5\ArcToolbox\Toolboxes\Data Management Tools.tbx\CalculateField" Date="20231128" Time="174113">CalculateField union2_merge Name2 "G_G1" VB #</Process><Process ToolSource="c:\program files (x86)\arcgis\desktop10.5\ArcToolbox\Toolboxes\Data Management Tools.tbx\CalculateField" Date="20231128" Time="174124">CalculateField union2_merge Name2 "H_G1" VB #</Process><Process ToolSource="c:\program files (x86)\arcgis\desktop10.5\ArcToolbox\Toolboxes\Data Management Tools.tbx\CalculateField" Date="20231128" Time="174150">CalculateField union2_merge Name2 "B_B10_G" VB #</Process><Process ToolSource="c:\program files (x86)\arcgis\desktop10.5\ArcToolbox\Toolboxes\Data Management Tools.tbx\CalculateField" Date="20231128" Time="174213">CalculateField union2_merge Name2 "A_B10_A8" VB #</Process><Process ToolSource="c:\program files (x86)\arcgis\desktop10.5\ArcToolbox\Toolboxes\Data Management Tools.tbx\CalculateField" Date="20231128" Time="174236">CalculateField union2_merge Name2 "A_B11_A9" VB #</Process><Process ToolSource="c:\program files (x86)\arcgis\desktop10.5\ArcToolbox\Toolboxes\Data Management Tools.tbx\CalculateField" Date="20231128" Time="174254">CalculateField union2_merge Name2 "B_B11_H" VB #</Process><Process ToolSource="c:\program files (x86)\arcgis\desktop10.5\ArcToolbox\Toolboxes\Data Management Tools.tbx\CalculateField" Date="20231128" Time="174406">CalculateField union2_merge Name2 "A_B9_A7" VB #</Process><Process ToolSource="c:\program files (x86)\arcgis\desktop10.5\ArcToolbox\Toolboxes\Data Management Tools.tbx\CalculateField" Date="20231128" Time="174418">CalculateField union2_merge Name2 "B_B9" VB #</Process><Process ToolSource="c:\program files (x86)\arcgis\desktop10.5\ArcToolbox\Toolboxes\Data Management Tools.tbx\CalculateField" Date="20231128" Time="174434">CalculateField union2_merge Name2 "B_T20" VB #</Process><Process ToolSource="c:\program files (x86)\arcgis\desktop10.5\ArcToolbox\Toolboxes\Data Management Tools.tbx\CalculateField" Date="20231128" Time="174447">CalculateField union2_merge Name2 "B_B8" VB #</Process><Process ToolSource="c:\program files (x86)\arcgis\desktop10.5\ArcToolbox\Toolboxes\Data Management Tools.tbx\CalculateField" Date="20231128" Time="174510">CalculateField union2_merge Name2 "A_A6_B8" VB #</Process><Process ToolSource="c:\program files (x86)\arcgis\desktop10.5\ArcToolbox\Toolboxes\Data Management Tools.tbx\CalculateField" Date="20231128" Time="174534">CalculateField union2_merge Name2 "T15_B8" VB #</Process><Process ToolSource="c:\program files (x86)\arcgis\desktop10.5\ArcToolbox\Toolboxes\Data Management Tools.tbx\CalculateField" Date="20231128" Time="174618">CalculateField union2_merge Name2 "T11_B8_704" VB #</Process><Process ToolSource="c:\program files (x86)\arcgis\desktop10.5\ArcToolbox\Toolboxes\Data Management Tools.tbx\CalculateField" Date="20231128" Time="174636">CalculateField union2_merge Name2 "T10_B8" VB #</Process><Process ToolSource="c:\program files (x86)\arcgis\desktop10.5\ArcToolbox\Toolboxes\Data Management Tools.tbx\CalculateField" Date="20231128" Time="174725">CalculateField union2_merge Name2 "T10_T20" VB #</Process><Process ToolSource="c:\program files (x86)\arcgis\desktop10.5\ArcToolbox\Toolboxes\Data Management Tools.tbx\CalculateField" Date="20231128" Time="174747">CalculateField union2_merge Name2 "A_B7" VB #</Process><Process ToolSource="c:\program files (x86)\arcgis\desktop10.5\ArcToolbox\Toolboxes\Data Management Tools.tbx\CalculateField" Date="20231128" Time="183332">CalculateField union2_merge Name2 "B_B7" VB #</Process><Process ToolSource="c:\program files (x86)\arcgis\desktop10.5\ArcToolbox\Toolboxes\Data Management Tools.tbx\CalculateField" Date="20231128" Time="183356">CalculateField union2_merge Name2 "A_A5_B6" VB #</Process><Process ToolSource="c:\program files (x86)\arcgis\desktop10.5\ArcToolbox\Toolboxes\Data Management Tools.tbx\CalculateField" Date="20231128" Time="183442">CalculateField union2_merge Name2 "T5_B7" VB #</Process><Process ToolSource="c:\program files (x86)\arcgis\desktop10.5\ArcToolbox\Toolboxes\Data Management Tools.tbx\CalculateField" Date="20231128" Time="183456">CalculateField union2_merge Name2 "" VB #</Process><Process ToolSource="c:\program files (x86)\arcgis\desktop10.5\ArcToolbox\Toolboxes\Data Management Tools.tbx\CalculateField" Date="20231128" Time="183508">CalculateField union2_merge Name2 "" VB #</Process><Process ToolSource="c:\program files (x86)\arcgis\desktop10.5\ArcToolbox\Toolboxes\Data Management Tools.tbx\CalculateField" Date="20231128" Time="183545">CalculateField union2_merge Name2 "T5_B6" VB #</Process><Process ToolSource="c:\program files (x86)\arcgis\desktop10.5\ArcToolbox\Toolboxes\Data Management Tools.tbx\CalculateField" Date="20231128" Time="183605">CalculateField union2_merge Name2 "T5_B5" VB #</Process><Process ToolSource="c:\program files (x86)\arcgis\desktop10.5\ArcToolbox\Toolboxes\Data Management Tools.tbx\CalculateField" Date="20231128" Time="183623">CalculateField union2_merge Name2 "A_B5" VB #</Process><Process ToolSource="c:\program files (x86)\arcgis\desktop10.5\ArcToolbox\Toolboxes\Data Management Tools.tbx\CalculateField" Date="20231128" Time="183637">CalculateField union2_merge Name2 "B_B5" VB #</Process><Process ToolSource="c:\program files (x86)\arcgis\desktop10.5\ArcToolbox\Toolboxes\Data Management Tools.tbx\CalculateField" Date="20231128" Time="183715">CalculateField union2_merge Name2 "A_A4_B4" VB #</Process><Process ToolSource="c:\program files (x86)\arcgis\desktop10.5\ArcToolbox\Toolboxes\Data Management Tools.tbx\CalculateField" Date="20231128" Time="183733">CalculateField union2_merge Name2 "B_B4" VB #</Process><Process ToolSource="c:\program files (x86)\arcgis\desktop10.5\ArcToolbox\Toolboxes\Data Management Tools.tbx\CalculateField" Date="20231128" Time="183814">CalculateField union2_merge Name2 "A_A3_B3" VB #</Process><Process ToolSource="c:\program files (x86)\arcgis\desktop10.5\ArcToolbox\Toolboxes\Data Management Tools.tbx\CalculateField" Date="20231128" Time="183844">CalculateField union2_merge Name2 "B_B3" VB #</Process><Process ToolSource="c:\program files (x86)\arcgis\desktop10.5\ArcToolbox\Toolboxes\Data Management Tools.tbx\CalculateField" Date="20231128" Time="183919">CalculateField union2_merge Name2 "B2_B_F" VB #</Process><Process ToolSource="c:\program files (x86)\arcgis\desktop10.5\ArcToolbox\Toolboxes\Data Management Tools.tbx\CalculateField" Date="20231128" Time="183940">CalculateField union2_merge Name2 "A_A2_B2" VB #</Process><Process ToolSource="c:\program files (x86)\arcgis\desktop10.5\ArcToolbox\Toolboxes\Data Management Tools.tbx\CalculateField" Date="20231128" Time="184000">CalculateField union2_merge Name2 "A_B1_A1" VB #</Process><Process ToolSource="c:\program files (x86)\arcgis\desktop10.5\ArcToolbox\Toolboxes\Data Management Tools.tbx\CalculateField" Date="20231128" Time="184019">CalculateField union2_merge Name2 "B_B1" VB #</Process><Process ToolSource="c:\program files (x86)\arcgis\desktop10.5\ArcToolbox\Toolboxes\Data Management Tools.tbx\CalculateField" Date="20231128" Time="184041">CalculateField union2_merge Name2 "E_T4" VB #</Process><Process ToolSource="c:\program files (x86)\arcgis\desktop10.5\ArcToolbox\Toolboxes\Data Management Tools.tbx\CalculateField" Date="20231128" Time="184056">CalculateField union2_merge Name2 "F_T4" VB #</Process><Process ToolSource="c:\program files (x86)\arcgis\desktop10.5\ArcToolbox\Toolboxes\Data Management Tools.tbx\CalculateField" Date="20231128" Time="184114">CalculateField union2_merge Name2 "B_E" VB #</Process><Process ToolSource="c:\program files (x86)\arcgis\desktop10.5\ArcToolbox\Toolboxes\Data Management Tools.tbx\CalculateField" Date="20231128" Time="184139">CalculateField union2_merge Name2 "T2_T3" VB #</Process><Process ToolSource="c:\program files (x86)\arcgis\desktop10.5\ArcToolbox\Toolboxes\Data Management Tools.tbx\CalculateField" Date="20231128" Time="184154">CalculateField union2_merge Name2 "T4_T3" VB #</Process><Process ToolSource="c:\program files (x86)\arcgis\desktop10.5\ArcToolbox\Toolboxes\Data Management Tools.tbx\CalculateField" Date="20231128" Time="184207">CalculateField union2_merge Name2 "B_T3" VB #</Process><Process ToolSource="c:\program files (x86)\arcgis\desktop10.5\ArcToolbox\Toolboxes\Data Management Tools.tbx\CalculateField" Date="20231128" Time="184230">CalculateField union2_merge Name2 "T1_T4" VB #</Process><Process ToolSource="c:\program files (x86)\arcgis\desktop10.5\ArcToolbox\Toolboxes\Data Management Tools.tbx\CalculateField" Date="20231128" Time="184243">CalculateField union2_merge Name2 "B_T1" VB #</Process><Process ToolSource="c:\program files (x86)\arcgis\desktop10.5\ArcToolbox\Toolboxes\Data Management Tools.tbx\CalculateField" Date="20231128" Time="184254">CalculateField union2_merge Name2 "T2_T1" VB #</Process><Process ToolSource="c:\program files (x86)\arcgis\desktop10.5\ArcToolbox\Toolboxes\Data Management Tools.tbx\CalculateField" Date="20231128" Time="184328">CalculateField union2_merge Name2 "" VB #</Process><Process ToolSource="c:\program files (x86)\arcgis\desktop10.5\ArcToolbox\Toolboxes\Data Management Tools.tbx\CalculateField" Date="20231128" Time="184348">CalculateField union2_merge Name2 "C3_T8" VB #</Process><Process ToolSource="c:\program files (x86)\arcgis\desktop10.5\ArcToolbox\Toolboxes\Data Management Tools.tbx\CalculateField" Date="20231128" Time="184433">CalculateField union2_merge Name2 "N9_T8" VB #</Process><Process ToolSource="c:\program files (x86)\arcgis\desktop10.5\ArcToolbox\Toolboxes\Data Management Tools.tbx\CalculateField" Date="20231128" Time="184452">CalculateField union2_merge Name2 "N7_T8" VB #</Process><Process ToolSource="c:\program files (x86)\arcgis\desktop10.5\ArcToolbox\Toolboxes\Data Management Tools.tbx\CalculateField" Date="20231128" Time="184509">CalculateField union2_merge Name2 "C4_T8" VB #</Process><Process ToolSource="c:\program files (x86)\arcgis\desktop10.5\ArcToolbox\Toolboxes\Data Management Tools.tbx\CalculateField" Date="20231128" Time="184535">CalculateField union2_merge Name2 "C4_N10" VB #</Process><Process ToolSource="c:\program files (x86)\arcgis\desktop10.5\ArcToolbox\Toolboxes\Data Management Tools.tbx\CalculateField" Date="20231128" Time="184547">CalculateField union2_merge Name2 "C4_N8" VB #</Process><Process ToolSource="c:\program files (x86)\arcgis\desktop10.5\ArcToolbox\Toolboxes\Data Management Tools.tbx\CalculateField" Date="20231128" Time="184643">CalculateField union2_merge Name2 "" VB #</Process><Process ToolSource="c:\program files (x86)\arcgis\desktop10.5\ArcToolbox\Toolboxes\Data Management Tools.tbx\CalculateField" Date="20231128" Time="184708">CalculateField union2_merge Name2 "N7_N10" VB #</Process><Process ToolSource="c:\program files (x86)\arcgis\desktop10.5\ArcToolbox\Toolboxes\Data Management Tools.tbx\CalculateField" Date="20231128" Time="184908">CalculateField union2_merge Name2 "N7_N8" VB #</Process><Process ToolSource="c:\program files (x86)\arcgis\desktop10.5\ArcToolbox\Toolboxes\Data Management Tools.tbx\CalculateField" Date="20231128" Time="184936">CalculateField union2_merge Name2 "C6_T8" VB #</Process><Process ToolSource="c:\program files (x86)\arcgis\desktop10.5\ArcToolbox\Toolboxes\Data Management Tools.tbx\CalculateField" Date="20231128" Time="185006">CalculateField union2_merge Name2 "C7_G3" VB #</Process><Process ToolSource="c:\program files (x86)\arcgis\desktop10.5\ArcToolbox\Toolboxes\Data Management Tools.tbx\CalculateField" Date="20231128" Time="185059">CalculateField union2_merge Name2 "C7_N4" VB #</Process><Process ToolSource="c:\program files (x86)\arcgis\desktop10.5\ArcToolbox\Toolboxes\Data Management Tools.tbx\CalculateField" Date="20231128" Time="185120">CalculateField union2_merge Name2 "T8_N1" VB #</Process><Process ToolSource="c:\program files (x86)\arcgis\desktop10.5\ArcToolbox\Toolboxes\Data Management Tools.tbx\CalculateField" Date="20231128" Time="185342">CalculateField union2_merge Name2 "G3_N1" VB #</Process><Process ToolSource="c:\program files (x86)\arcgis\desktop10.5\ArcToolbox\Toolboxes\Data Management Tools.tbx\CalculateField" Date="20231128" Time="185408">CalculateField union2_merge Name2 "C_N13" VB #</Process><Process ToolSource="c:\program files (x86)\arcgis\desktop10.5\ArcToolbox\Toolboxes\Data Management Tools.tbx\CalculateField" Date="20231128" Time="185418">CalculateField union2_merge Name2 "C_N11" VB #</Process><Process ToolSource="c:\program files (x86)\arcgis\desktop10.5\ArcToolbox\Toolboxes\Data Management Tools.tbx\CalculateField" Date="20231128" Time="185510">CalculateField union2_merge Name2 "B_B6" VB #</Process><Process ToolSource="c:\program files (x86)\arcgis\desktop10.5\ArcToolbox\Toolboxes\Data Management Tools.tbx\CalculateField" Date="20231229" Time="141658">CalculateField network LimitVA 13 VB #</Process><Process ToolSource="c:\program files (x86)\arcgis\desktop10.5\ArcToolbox\Toolboxes\Data Management Tools.tbx\CalculateField" Date="20231229" Time="141723">CalculateField network LimitVD 0 VB #</Process><Process ToolSource="c:\program files (x86)\arcgis\desktop10.5\ArcToolbox\Toolboxes\Data Management Tools.tbx\CalculateField" Date="20231229" Time="141825">CalculateField network LimitVA 10 VB #</Process><Process ToolSource="c:\program files (x86)\arcgis\desktop10.5\ArcToolbox\Toolboxes\Data Management Tools.tbx\CalculateField" Date="20231229" Time="141839">CalculateField network LimitVD 0 VB #</Process><Process ToolSource="c:\program files (x86)\arcgis\desktop10.5\ArcToolbox\Toolboxes\Data Management Tools.tbx\CalculateField" Date="20231229" Time="150931">CalculateField network LimitVD 1 VB #</Process><Process ToolSource="c:\program files (x86)\arcgis\desktop10.5\ArcToolbox\Toolboxes\Data Management Tools.tbx\CalculateField" Date="20231229" Time="151042">CalculateField network LimitVA 13 VB #</Process><Process ToolSource="c:\program files (x86)\arcgis\desktop10.5\ArcToolbox\Toolboxes\Data Management Tools.tbx\CalculateField" Date="20231229" Time="151332">CalculateField network LimitVA 10 VB #</Process><Process ToolSource="c:\program files (x86)\arcgis\desktop10.5\ArcToolbox\Toolboxes\Data Management Tools.tbx\CalculateField" Date="20231229" Time="151337">CalculateField network LimitVD 10 VB #</Process><Process ToolSource="c:\program files (x86)\arcgis\desktop10.5\ArcToolbox\Toolboxes\Data Management Tools.tbx\CalculateField" Date="20240109" Time="202139">CalculateField network Direction "twoway" VB #</Process><Process ToolSource="c:\program files (x86)\arcgis\desktop10.5\ArcToolbox\Toolboxes\Data Management Tools.tbx\CalculateField" Date="20240319" Time="135004">CalculateField network id [FID] VB #</Process><Process ToolSource="c:\program files (x86)\arcgis\desktop10.5\ArcToolbox\Toolboxes\Data Management Tools.tbx\CalculateField" Date="20240319" Time="135039">CalculateField network id [FID] VB #</Process><Process ToolSource="c:\program files (x86)\arcgis\desktop10.5\ArcToolbox\Toolboxes\Data Management Tools.tbx\CalculateField" Date="20240319" Time="135101">CalculateField network id [FID]+0 VB #</Process><Process ToolSource="c:\program files (x86)\arcgis\desktop10.5\ArcToolbox\Toolboxes\Data Management Tools.tbx\CalculateField" Date="20240319" Time="135120">CalculateField network id [FID]+0 VB #</Process><Process ToolSource="c:\program files (x86)\arcgis\desktop10.5\ArcToolbox\Toolboxes\Data Management Tools.tbx\CalculateField" Date="20240319" Time="135557">CalculateField network id [FID] VB #</Process><Process ToolSource="c:\program files (x86)\arcgis\desktop10.5\ArcToolbox\Toolboxes\Data Management Tools.tbx\CalculateField" Date="20240319" Time="135627">CalculateField network ids ""road"+ [id]" VB #</Process><Process ToolSource="c:\program files (x86)\arcgis\desktop10.5\ArcToolbox\Toolboxes\Data Management Tools.tbx\CalculateField" Date="20240319" Time="135648">CalculateField network id [ids] VB #</Process><Process ToolSource="c:\program files (x86)\arcgis\desktop10.5\ArcToolbox\Toolboxes\Data Management Tools.tbx\CalculateField" Date="20240319" Time="135726">CalculateField network ids "r" VB #</Process><Process ToolSource="c:\program files (x86)\arcgis\desktop10.5\ArcToolbox\Toolboxes\Data Management Tools.tbx\CalculateField" Date="20240319" Time="135734">CalculateField network id [FID] VB #</Process><Process ToolSource="c:\program files (x86)\arcgis\desktop10.5\ArcToolbox\Toolboxes\Data Management Tools.tbx\CalculateField" Date="20240319" Time="135803">CalculateField network ids ""r"+ [id]" VB #</Process><Process ToolSource="c:\program files (x86)\arcgis\desktop10.5\ArcToolbox\Toolboxes\Data Management Tools.tbx\CalculateField" Date="20240319" Time="135814">CalculateField network id [ids] VB #</Process><Process ToolSource="c:\program files (x86)\arcgis\desktop10.5\ArcToolbox\Toolboxes\Data Management Tools.tbx\CalculateField" Date="20240425" Time="000535">CalculateField network VS_runway [runwayV] VB #</Process><Process ToolSource="c:\program files (x86)\arcgis\desktop10.5\ArcToolbox\Toolboxes\Data Management Tools.tbx\CalculateField" Date="20240427" Time="165557">CalculateField network VS_runway "LimitD" VB #</Process><Process ToolSource="c:\program files (x86)\arcgis\desktop10.5\ArcToolbox\Toolboxes\Data Management Tools.tbx\CalculateField" Date="20240427" Time="165733">CalculateField network VS_runway "\'LimitD\'" VB #</Process><Process ToolSource="c:\program files (x86)\arcgis\desktop10.5\ArcToolbox\Toolboxes\Data Management Tools.tbx\CalculateField" Date="20240427" Time="165901">CalculateField network VS_runway "" VB #</Process></lineage></DataProperties></Esri></metadata>
